plaquette_graph_bindings.cpython-311-darwin.so
plaquette_graph-0.0.1a0.dist-info/RECORD
plaquette_graph-0.0.1a0.dist-info/LICENSE
plaquette_graph-0.0.1a0.dist-info/WHEEL
plaquette_graph-0.0.1a0.dist-info/top_level.txt
plaquette_graph-0.0.1a0.dist-info/METADATA
plaquette_graph/__init__.py
