Metadata-Version: 2.1
Name: plaquette-graph
Version: 0.0.1a0
Project-URL: Homepage, https://docs.plaquette.design/projects/graph
Project-URL: Bug Tracker, https://github.com/qc-design/plaquette-graph/issues
Classifier: Development Status :: 3 - Alpha
Classifier: Intended Audience :: Developers
Classifier: Intended Audience :: Science/Research
Classifier: License :: OSI Approved :: Apache Software License
Classifier: Natural Language :: English
Classifier: Programming Language :: Python :: 3
Classifier: Programming Language :: Python :: 3.10
Requires-Python: >=3.10
License-File: LICENSE
Requires-Dist: pybind11
Requires-Dist: pytest
Requires-Dist: pytest-cov
Requires-Dist: pytest-mock
Requires-Dist: numpy
